fastpy_rest/__init__.py
fastpy_rest/core.py
fastpy_rest/exceptions.py
fastpy_rest/main.py
fastpy_rest/params.py
fastpy_rest/requests.py
fastpy_rest/responses.py
fastpy_rest/status_codes.py
fastpy_rest-0.1.3.dist-info/LICENSE
fastpy_rest-0.1.3.dist-info/METADATA
fastpy_rest-0.1.3.dist-info/WHEEL
fastpy_rest-0.1.3.dist-info/top_level.txt
fastpy_rest-0.1.3.dist-info/RECORD
