Metadata-Version: 2.1
Name: fastpy-rest
Version: 0.1.3
Summary: FastPy-Rest is a minimalisitc lightweight framework to create restapis easily.
Home-page: https://github.com/sineshashi/FastPy-Rest
Author: Shashi Kant
Author-email: shashikantrbl123@gmail.com
License-File: LICENSE
Requires-Dist: pydantic (>=2.1.1)
